botdash/__init__.py
botdash/client.py
botdash/lib/__init__.py
botdash/lib/util/__init__.py
botdash/lib/util/exceptions.py
botdash/lib/util/objects.py
botdash.pro-0.0.2.dist-info/LICENSE
botdash.pro-0.0.2.dist-info/METADATA
botdash.pro-0.0.2.dist-info/WHEEL
botdash.pro-0.0.2.dist-info/top_level.txt
botdash.pro-0.0.2.dist-info/RECORD
