Metadata-Version: 2.1
Name: botdash.pro
Version: 0.0.2
Summary: API wrapper for BotDash
Home-page: UNKNOWN
Author: Seer#6054
Author-email: admin@seer-software.com
License: MIT
Keywords: BotDash,discord,dashboard,official
Platform: UNKNOWN
Requires-Dist: setuptools
Requires-Dist: requests
Requires-Dist: six
Requires-Dist: ujson
